xinv/__init__.py
xinv/config.py
xinv/exceptions.py
xinv/filters.py
xinv/main.py
xinv/models.py
xinv/renderer.py
xinv/assets/__init__.py
xinv/assets/style.css
xinv/assets/template.html
xinv-0.1.0.dist-info/LICENSE
xinv-0.1.0.dist-info/METADATA
xinv-0.1.0.dist-info/WHEEL
xinv-0.1.0.dist-info/entry_points.txt
xinv-0.1.0.dist-info/top_level.txt
xinv-0.1.0.dist-info/RECORD
