Metadata-Version: 2.1
Name: xinv
Version: 0.1.0
Summary: A CLI tool for generating customized invoices
Author-email: Kamil Turek <kamil.turek@hotmail.com>
License: MIT
Keywords: cli,invoice
Classifier: Environment :: Console
Classifier: License :: OSI Approved :: MIT License
Classifier: Operating System :: MacOS
Classifier: Programming Language :: Python :: 3
Classifier: Programming Language :: Python :: 3.8
Classifier: Programming Language :: Python :: 3.9
Classifier: Programming Language :: Python :: 3.10
Classifier: Programming Language :: Python :: 3.11
Requires-Python: >=3.8
License-File: LICENSE
Requires-Dist: click
Requires-Dist: Jinja2
Requires-Dist: pdfkit
Requires-Dist: pydantic (<2)
Provides-Extra: dev
Requires-Dist: pytest ; extra == 'dev'
Requires-Dist: pytest-cov ; extra == 'dev'
Requires-Dist: diff-pdf-visually ; extra == 'dev'
